kgdata/__init__.py
kgdata/config.py
kgdata/dataset.py
kgdata/db.py
kgdata/dbpedia/__init__.py
kgdata/dbpedia/__main__.py
kgdata/dbpedia/config.py
kgdata/dbpedia/datasets/__init__.py
kgdata/dbpedia/datasets/__main__.py
kgdata/dbpedia/datasets/class_count.py
kgdata/dbpedia/datasets/classes.py
kgdata/dbpedia/datasets/entities.py
kgdata/dbpedia/datasets/entity_all_types.py
kgdata/dbpedia/datasets/entity_degrees.py
kgdata/dbpedia/datasets/entity_labels.py
kgdata/dbpedia/datasets/entity_metadata.py
kgdata/dbpedia/datasets/entity_redirections.py
kgdata/dbpedia/datasets/entity_types.py
kgdata/dbpedia/datasets/entity_types_and_degrees.py
kgdata/dbpedia/datasets/generic_extractor_dump.py
kgdata/dbpedia/datasets/mapping_extractor_dump.py
kgdata/dbpedia/datasets/meta_graph.py
kgdata/dbpedia/datasets/meta_graph_stats.py
kgdata/dbpedia/datasets/ontology_dump.py
kgdata/dbpedia/datasets/page_id_dump.py
kgdata/dbpedia/datasets/page_ids.py
kgdata/dbpedia/datasets/properties.py
kgdata/dbpedia/datasets/wikilink_dump.py
kgdata/dbpedia/datasets/wikilinks.py
kgdata/misc/__init__.py
kgdata/misc/download.py
kgdata/misc/funcs.py
kgdata/misc/hierarchy.py
kgdata/misc/modification.py
kgdata/misc/ntriples_parser.py
kgdata/misc/optional_import.py
kgdata/misc/query.py
kgdata/misc/resource.py
kgdata/models/__init__.py
kgdata/models/entity.py
kgdata/models/multilingual.py
kgdata/models/ont_class.py
kgdata/models/ont_property.py
kgdata/models/ontology.py
kgdata/py.typed
kgdata/spark/__init__.py
kgdata/spark/common.py
kgdata/spark/extended_rdd.py
kgdata/spark/rdd_alike.py
kgdata/splitter.py
kgdata/wikidata/__init__.py
kgdata/wikidata/__main__.py
kgdata/wikidata/config.py
kgdata/wikidata/datasets/__init__.py
kgdata/wikidata/datasets/__main__.py
kgdata/wikidata/datasets/acyclic_classes.py
kgdata/wikidata/datasets/class_count.py
kgdata/wikidata/datasets/classes.py
kgdata/wikidata/datasets/cross_wiki_mapping.py
kgdata/wikidata/datasets/entities.py
kgdata/wikidata/datasets/entity_all_types.py
kgdata-7.0.12.dist-info/METADATA
kgdata-7.0.12.dist-info/WHEEL
kgdata-7.0.12.dist-info/licenses/LICENSE
kgdata-7.0.12.dist-info/RECORD
